data = {
"type": "FeatureCollection",
"name": "wt_centroid",
"crs": { "type": "name", "properties": { "name": "urn:ogc:def:crs:OGC:1.3:CRS84" } },
"features": [
{ "type": "Feature", "properties": { "OFFICIAL_N": "67", "field_2": "2848" }, "geometry": { "type": "Point", "coordinates": [ -76.282591986790237, 44.593678577565107 ] } },
{ "type": "Feature", "properties": { "OFFICIAL_N": "80", "field_2": "3625" }, "geometry": { "type": "Point", "coordinates": [ -80.484569021664925, 43.694564147936049 ] } },
{ "type": "Feature", "properties": { "OFFICIAL_N": "73", "field_2": "3688" }, "geometry": { "type": "Point", "coordinates": [ -78.623809385358555, 44.187853827693694 ] } },
{ "type": "Feature", "properties": { "OFFICIAL_N": "42", "field_2": "10" }, "geometry": { "type": "Point", "coordinates": [ -80.989440172033781, 46.211199273049615 ] } },
{ "type": "Feature", "properties": { "OFFICIAL_N": "58", "field_2": "335" }, "geometry": { "type": "Point", "coordinates": [ -77.249756186848003, 45.366474191381876 ] } },
{ "type": "Feature", "properties": { "OFFICIAL_N": "59", "field_2": "2655" }, "geometry": { "type": "Point", "coordinates": [ -76.824302461984075, 45.558217113251509 ] } },
{ "type": "Feature", "properties": { "OFFICIAL_N": "75", "field_2": "1747" }, "geometry": { "type": "Point", "coordinates": [ -78.807410947055217, 44.518249031063419 ] } },
{ "type": "Feature", "properties": { "OFFICIAL_N": "60", "field_2": "1439" }, "geometry": { "type": "Point", "coordinates": [ -78.101894005911092, 44.725655146576521 ] } },
{ "type": "Feature", "properties": { "OFFICIAL_N": "84", "field_2": "3487" }, "geometry": { "type": "Point", "coordinates": [ -81.670339617704784, 44.381492737450309 ] } },
{ "type": "Feature", "properties": { "OFFICIAL_N": "50", "field_2": "30" }, "geometry": { "type": "Point", "coordinates": [ -79.160108933995915, 45.615714273448162 ] } },
{ "type": "Feature", "properties": { "OFFICIAL_N": "83A", "field_2": "278" }, "geometry": { "type": "Point", "coordinates": [ -81.649485385036996, 45.067581938502379 ] } },
{ "type": "Feature", "properties": { "OFFICIAL_N": "47", "field_2": "10" }, "geometry": { "type": "Point", "coordinates": [ -79.885002228202012, 45.943137621431767 ] } },
{ "type": "Feature", "properties": { "OFFICIAL_N": "70", "field_2": "1245" }, "geometry": { "type": "Point", "coordinates": [ -77.1742251029942, 43.870107272832009 ] } },
{ "type": "Feature", "properties": { "OFFICIAL_N": "71", "field_2": "942" }, "geometry": { "type": "Point", "coordinates": [ -77.76356360851311, 44.061758440667703 ] } },
{ "type": "Feature", "properties": { "OFFICIAL_N": "88", "field_2": "283" }, "geometry": { "type": "Point", "coordinates": [ -79.390807161787947, 43.230913625945149 ] } },
{ "type": "Feature", "properties": { "OFFICIAL_N": "49", "field_2": "168" }, "geometry": { "type": "Point", "coordinates": [ -79.775527587112649, 45.505815581426198 ] } },
{ "type": "Feature", "properties": { "OFFICIAL_N": "95", "field_2": "569" }, "geometry": { "type": "Point", "coordinates": [ -82.657710323353001, 41.77652086956062 ] } },
{ "type": "Feature", "properties": { "OFFICIAL_N": "61", "field_2": "353" }, "geometry": { "type": "Point", "coordinates": [ -77.437724026668761, 44.86372593199512 ] } },
{ "type": "Feature", "properties": { "OFFICIAL_N": "54", "field_2": "82" }, "geometry": { "type": "Point", "coordinates": [ -78.566443802901176, 45.278281749811008 ] } },
{ "type": "Feature", "properties": { "OFFICIAL_N": "46", "field_2": "137" }, "geometry": { "type": "Point", "coordinates": [ -80.43001723367, 45.371243780099562 ] } },
{ "type": "Feature", "properties": { "OFFICIAL_N": "48", "field_2": "218" }, "geometry": { "type": "Point", "coordinates": [ -78.340894825532047, 46.09990305638874 ] } },
{ "type": "Feature", "properties": { "OFFICIAL_N": "57", "field_2": "191" }, "geometry": { "type": "Point", "coordinates": [ -77.869053913419592, 45.203920037278294 ] } },
{ "type": "Feature", "properties": { "OFFICIAL_N": "62", "field_2": "522" }, "geometry": { "type": "Point", "coordinates": [ -76.944453444019629, 44.667466311139378 ] } },
{ "type": "Feature", "properties": { "OFFICIAL_N": "36", "field_2": "57" }, "geometry": { "type": "Point", "coordinates": [ -84.308237316580815, 46.7912261234369 ] } },
{ "type": "Feature", "properties": { "OFFICIAL_N": "56", "field_2": "653" }, "geometry": { "type": "Point", "coordinates": [ -78.702503660504206, 44.95530793841106 ] } },
{ "type": "Feature", "properties": { "OFFICIAL_N": "65", "field_2": "6828" }, "geometry": { "type": "Point", "coordinates": [ -75.03610522712313, 45.273440059027337 ] } },
{ "type": "Feature", "properties": { "OFFICIAL_N": "45", "field_2": "520" }, "geometry": { "type": "Point", "coordinates": [ -83.923046380024246, 46.199600772245525 ] } },
{ "type": "Feature", "properties": { "OFFICIAL_N": "66A", "field_2": "1625" }, "geometry": { "type": "Point", "coordinates": [ -75.70115720097111, 44.830433396637332 ] } }
]
}
